orme/__init__.py
orme/__main__.py
orme/cli.py
orme/constants.py
orme/settings.py
orme/utils.py
orme/validations.py
orme/db/common.py
orme/db/connection.py
orme/db/operations.py
orme/db/queries/common_queries.py
orme/db/queries/queries_debts.py
orme/db/queries/queries_expenses.py
orme/debt/__init__.py
orme/debt/commands.py
orme/debt/run_debt.py
orme/expenses/__init__.py
orme/expenses/commands.py
orme/expenses/run_expenses.py
orme/expenses/utils.py
orme-0.1.2.13.dist-info/LICENSE.md
orme-0.1.2.13.dist-info/METADATA
orme-0.1.2.13.dist-info/WHEEL
orme-0.1.2.13.dist-info/entry_points.txt
orme-0.1.2.13.dist-info/top_level.txt
orme-0.1.2.13.dist-info/RECORD
