Metadata-Version: 2.1
Name: orme
Version: 0.1.2.13
Summary: Orme Financial Manager
Author-email: Carlos Correa <carlosdcorrea3@gmail.com>
Maintainer-email: Carlos Correa <carlosdcorrea3@gmail.com>
Project-URL: Homepage, https://github.com/CarlosDCorrea/orme
Project-URL: Documentation, https://github.com/CarlosDCorrea/orme
Project-URL: Repository, https://github.com/CarlosDCorrea/orme
Project-URL: Issues, https://github.com/CarlosDCorrea/orme/issues
Keywords: financial,manager
Classifier: Development Status :: 4 - Beta
Classifier: Intended Audience :: End Users/Desktop
Classifier: Topic :: Software Development :: Build Tools
Classifier: Environment :: Console
Classifier: License :: OSI Approved :: MIT License
Classifier: Programming Language :: Python :: 3.9
Requires-Python: >=3.9
License-File: LICENSE.md
Requires-Dist: pandas ==2.1.2
